parutils/__init__.py
parutils/changelog.py
parutils/csvl.py
parutils/dq.py
parutils/file.py
parutils/g.py
parutils/msc.py
parutils/strg.py
parutils/te.py
parutils/wrap.py
parutils/logging/__init__.py
parutils/logging/cl.py
parutils/logging/const.py
parutils/logging/core.py
parutils/logging/g.py
parutils/logging/logger.py
parutils/logging/main.py
parutils/logging/sl.py
parutils/tests/conftest.py
parutils/tests/test_csv.py
parutils/tests/test_dq.py
parutils/tests/test_file.py
parutils/tests/test_msc.py
parutils/tests/logging/check_log.py
parutils/tests/logging/test_logging.py
parutils/tests/string/check_log.py
parutils/tests/string/test_string.py
parutils-1.2.8.dist-info/licenses/LICENSE
parutils-1.2.8.dist-info/METADATA
parutils-1.2.8.dist-info/WHEEL
parutils-1.2.8.dist-info/top_level.txt
parutils-1.2.8.dist-info/RECORD
