Metadata-Version: 2.4
Name: ParUtils
Version: 1.2.8
Summary: This package contains a bunch of Python utilities developed for Support, Test and Automation IT Engineers
Author-email: Paul ARNAUD <paularnaud2@gmail.com>
Project-URL: Homepage, https://github.com/paularnaud2/ParUtils
Project-URL: Issues, https://github.com/paularnaud2/ParUtils/issues
Classifier: Programming Language :: Python :: 3
Classifier: Operating System :: OS Independent
Requires-Python: >=3.8
License-File: LICENSE
Dynamic: license-file
